{
  "title": "Fly Up",
  "artist": "RIIZE",
  "history": [
    {
      "timestamp": "2025-05-26T13:04:15.538388",
      "rank": 63
    },
    {
      "timestamp": "2025-05-26T14:04:13.429651",
      "rank": 62
    },
    {
      "timestamp": "2025-05-26T15:04:14.587521",
      "rank": 63
    },
    {
      "timestamp": "2025-05-26T16:04:13.565645",
      "rank": 61
    },
    {
      "timestamp": "2025-05-26T17:04:16.298973",
      "rank": 60
    },
    {
      "timestamp": "2025-05-26T18:04:17.176972",
      "rank": 58
    },
    {
      "timestamp": "2025-05-26T19:04:12.232998",
      "rank": 58
    },
    {
      "timestamp": "2025-05-26T20:04:12.275054",
      "rank": 57
    },
    {
      "timestamp": "2025-05-26T21:04:12.985473",
      "rank": 56
    },
    {
      "timestamp": "2025-05-26T22:04:12.907663",
      "rank": 56
    },
    {
      "timestamp": "2025-05-26T23:04:12.206731",
      "rank": 58
    },
    {
      "timestamp": "2025-05-27T00:04:12.870319",
      "rank": 56
    },
    {
      "timestamp": "2025-05-27T01:04:12.279466",
      "rank": 59
    },
    {
      "timestamp": "2025-05-27T02:04:11.982109",
      "rank": 59
    },
    {
      "timestamp": "2025-05-27T03:04:12.496345",
      "rank": 61
    },
    {
      "timestamp": "2025-05-27T04:04:11.357223",
      "rank": 61
    },
    {
      "timestamp": "2025-05-27T05:04:11.285933",
      "rank": 68
    },
    {
      "timestamp": "2025-05-27T06:04:12.056505",
      "rank": 71
    },
    {
      "timestamp": "2025-05-27T07:04:12.678193",
      "rank": 71
    },
    {
      "timestamp": "2025-05-27T08:04:11.071967",
      "rank": 73
    },
    {
      "timestamp": "2025-05-27T09:04:10.702850",
      "rank": 73
    },
    {
      "timestamp": "2025-05-27T10:04:15.503016",
      "rank": 59
    },
    {
      "timestamp": "2025-05-27T11:04:15.165421",
      "rank": 58
    },
    {
      "timestamp": "2025-05-27T12:04:15.631378",
      "rank": 62
    },
    {
      "timestamp": "2025-05-27T14:04:14.613214",
      "rank": 60
    },
    {
      "timestamp": "2025-05-27T15:04:14.365240",
      "rank": 60
    },
    {
      "timestamp": "2025-05-27T16:04:16.483491",
      "rank": 61
    },
    {
      "timestamp": "2025-05-27T17:04:13.735486",
      "rank": 61
    },
    {
      "timestamp": "2025-05-27T18:04:16.307209",
      "rank": 61
    },
    {
      "timestamp": "2025-05-27T19:04:15.576598",
      "rank": 61
    }
  ]
}