{
  "title": "Fly Up",
  "artist": "RIIZE",
  "history": [
    {
      "timestamp": "2025-05-29T18:04:15.664293",
      "rank": 71
    },
    {
      "timestamp": "2025-05-29T19:04:12.588150",
      "rank": 71
    },
    {
      "timestamp": "2025-05-29T20:04:13.664628",
      "rank": 71
    },
    {
      "timestamp": "2025-05-29T21:04:13.274102",
      "rank": 71
    },
    {
      "timestamp": "2025-05-29T22:04:13.692439",
      "rank": 73
    },
    {
      "timestamp": "2025-05-29T23:04:13.554191",
      "rank": 74
    },
    {
      "timestamp": "2025-05-30T00:04:13.960617",
      "rank": 74
    },
    {
      "timestamp": "2025-05-30T01:04:14.513985",
      "rank": 74
    },
    {
      "timestamp": "2025-05-30T02:04:13.245339",
      "rank": 74
    },
    {
      "timestamp": "2025-05-30T03:04:14.714585",
      "rank": 74
    },
    {
      "timestamp": "2025-05-30T04:04:13.266769",
      "rank": 78
    },
    {
      "timestamp": "2025-05-30T05:04:14.445259",
      "rank": 82
    },
    {
      "timestamp": "2025-05-30T06:04:12.392629",
      "rank": 83
    },
    {
      "timestamp": "2025-05-30T07:04:14.941797",
      "rank": 83
    },
    {
      "timestamp": "2025-05-30T08:04:12.935298",
      "rank": 86
    },
    {
      "timestamp": "2025-05-30T09:04:15.421232",
      "rank": 84
    },
    {
      "timestamp": "2025-05-30T10:04:15.727388",
      "rank": 82
    },
    {
      "timestamp": "2025-05-30T11:04:15.883993",
      "rank": 82
    },
    {
      "timestamp": "2025-05-30T12:04:14.836637",
      "rank": 82
    },
    {
      "timestamp": "2025-05-30T22:01:14.253700",
      "rank": 80
    },
    {
      "timestamp": "2025-05-30T23:04:13.740586",
      "rank": 80
    },
    {
      "timestamp": "2025-05-31T00:04:11.791535",
      "rank": 80
    },
    {
      "timestamp": "2025-05-31T01:04:11.926866",
      "rank": 81
    },
    {
      "timestamp": "2025-05-31T02:04:13.012780",
      "rank": 82
    },
    {
      "timestamp": "2025-05-31T03:04:13.167211",
      "rank": 82
    },
    {
      "timestamp": "2025-05-31T04:04:12.445253",
      "rank": 90
    },
    {
      "timestamp": "2025-05-31T05:04:11.991980",
      "rank": 90
    },
    {
      "timestamp": "2025-05-31T06:04:13.579991",
      "rank": 91
    },
    {
      "timestamp": "2025-05-31T07:04:13.453708",
      "rank": 92
    },
    {
      "timestamp": "2025-05-31T08:04:13.177917",
      "rank": 92
    },
    {
      "timestamp": "2025-05-31T09:04:13.250746",
      "rank": 92
    },
    {
      "timestamp": "2025-05-31T10:04:13.065559",
      "rank": 94
    }
  ]
}